Metadata-Version: 2.1
Name: mm-udawsml-distributions
Version: 0.1
Summary: Gaussian and Binomial distributions
Home-page: UNKNOWN
Author: margit
License: UNKNOWN
Platform: UNKNOWN
